cksp/__init__.py
cksp/algorithms/__init__.py
cksp/datatypes/__init__.py
cksp/utils/__init__.py
ksp/__init__.py
ksp/algorithms/__init__.py
ksp/algorithms/dijkstra.py
ksp/algorithms/utils.py
ksp/algorithms/yen.py
ksp/datatypes/__init__.py
ksp/datatypes/adjacency_dict.py
ksp/datatypes/priority_dict.py
ksp/utils/__init__.py
ksp/utils/config.py
ksp-0.0.5.dist-info/LICENSE
ksp-0.0.5.dist-info/METADATA
ksp-0.0.5.dist-info/WHEEL
ksp-0.0.5.dist-info/top_level.txt
ksp-0.0.5.dist-info/RECORD
