Metadata-Version: 2.1
Name: ksp
Version: 0.0.5
Summary: lightweight k-shortest paths
Home-page: https://gitlab.com/SumNeuron/ksp
Author: Sumner Magruder
Author-email: sumner.magruder@zmnh.uni-hamburg.de
License: UNKNOWN
Platform: UNKNOWN
Classifier: Programming Language :: Python :: 3.5
Classifier: License :: OSI Approved :: MIT License
Classifier: Operating System :: OS Independent
